MFLES/Conformal.py
MFLES/FeatureEngineering.py
MFLES/Forecaster.py
MFLES/Model.py
MFLES/__init__.py
MFLES/utils.py
MFLES-0.2.4.dist-info/LICENSE.txt
MFLES-0.2.4.dist-info/METADATA
MFLES-0.2.4.dist-info/WHEEL
MFLES-0.2.4.dist-info/top_level.txt
MFLES-0.2.4.dist-info/RECORD
