Metadata-Version: 2.1
Name: MFLES
Version: 0.2.4
Summary: Gradient boosted time series forecasting.
Home-page: https://github.com/tblume1992/MFLES
Author: Tyler Blume
Keywords: forecasting,time series,seasonality,trend
Classifier: Programming Language :: Python :: 3
Classifier: License :: OSI Approved :: MIT License
Classifier: Operating System :: OS Independent
License-File: LICENSE.txt
Requires-Dist: numpy
Requires-Dist: pandas
Requires-Dist: tqdm
Requires-Dist: numba
Requires-Dist: matplotlib
